AUTHORS.md
CHANGELOG.md
MANIFEST.in
README.md
README.txt
dev-requirements.in
requirements.in
setup.cfg
setup.py
flumel/__init__.py
flumel/cli.py
flumel/loggers.py
flumel/models.py
flumel/settings.py
flumel/tasks.py
flumel/tools.py
flumel.egg-info/PKG-INFO
flumel.egg-info/SOURCES.txt
flumel.egg-info/dependency_links.txt
flumel.egg-info/entry_points.txt
flumel.egg-info/requires.txt
flumel.egg-info/top_level.txt
flumel/templates/article.html
flumel/templates/email.html
flumel/templates/email.txt
flumel/templates/export.html
flumel/templates/page.html
flumel/templates/subscribe_choices.html
flumel/templates/subscribe_duplicate.html
flumel/templates/subscribe_invalid.html
flumel/templates/subscribe_success.html
flumel/templates/unsubscribe_failure.html
flumel/templates/unsubscribe_success.html