Metadata-Version: 1.1
Name: flumel
Version: 0.7.2
Summary: Encore un moyen de recevoir ses flux RSS par email
Home-page: https://gitlab.com/canarduck/flumel
Author: Canarduck
Author-email: renaud@canarduck.com
License: UNKNOWN
Keywords: rss email
Platform: UNKNOWN
Classifier: Programming Language :: Python :: 3
Classifier: Development Status :: 4 - Beta
Classifier: Environment :: Web Environment
Classifier: Intended Audience :: System Administrators
Classifier: License :: OSI Approved :: MIT License
Classifier: Operating System :: OS Independent
Classifier: Topic :: Communications :: Email
Classifier: Topic :: Internet :: WWW/HTTP :: Dynamic Content :: News/Diary
